flight_radar/__init__.py
flight_radar/clients/__init__.py
flight_radar/clients/api_client.py
flight_radar/dtos/__init__.py
flight_radar/dtos/airline.py
flight_radar/dtos/airport.py
flight_radar/dtos/api_usage.py
flight_radar/dtos/flight_position.py
flight_radar/dtos/flight_summary.py
flight_radar/dtos/flight_tracks.py
flight_radar/dtos/historic_flight_event.py
flight_radar/dtos/historic_position.py
flight_radar/dtos/live_flight_position.py
flight_radar/enums/enums.py
flight_radar/errors/__init__.py
flight_radar/errors/api_client.py
flight_radar/factory/__init__.py
flight_radar/factory/factory.py
flight_radar/models/__init__.py
flight_radar/models/airline.py
flight_radar/models/airport.py
flight_radar/models/api_usage.py
flight_radar/models/common.py
flight_radar/models/flight_position.py
flight_radar/models/flight_summary.py
flight_radar/models/flight_track.py
flight_radar/models/historic_flight_event.py
flight_radar/services/__init__.py
flight_radar/services/base.py
flight_radar/services/service.py
flight_radar-0.0.4.dist-info/licenses/LICENSE
flight_radar-0.0.4.dist-info/METADATA
flight_radar-0.0.4.dist-info/WHEEL
flight_radar-0.0.4.dist-info/top_level.txt
flight_radar-0.0.4.dist-info/RECORD
