Metadata-Version: 2.4
Name: flight-radar
Version: 0.0.4
Summary: An unofficial Python SDK for the FlightRadar24 API.
Author-email: Amir Muminovic <amir.muminovic192@gmail.com>
License: Copyright (c) 2025 <copyright holders>
Project-URL: Homepage, https://github.com/amirmuminovic/flight_radar
Project-URL: Documentation, https://amirmuminovic.github.io/flight_radar/
Project-URL: Repository, https://github.com/amirmuminovic/flight_radar
Project-URL: Bug Tracker, https://github.com/amirmuminovic/flight_radar/issues
Keywords: flight-radar,api,sdk,aviation,flights
Classifier: Intended Audience :: Developers
Classifier: License :: OSI Approved :: MIT License
Classifier: Programming Language :: Python :: 3
Classifier: Programming Language :: Python :: 3.12
Classifier: Operating System :: OS Independent
Classifier: Topic :: Software Development :: Libraries :: Python Modules
Requires-Python: >=3.12
License-File: LICENSE
Requires-Dist: pydantic>=2.11.5
Requires-Dist: requests>=2.32.4
Requires-Dist: pydantic-settings>=2.10.1
Requires-Dist: urllib3>=2.5.0
Provides-Extra: dev
Requires-Dist: pytest-cov>=6.2.1; extra == "dev"
Requires-Dist: pytest>=8.4.1; extra == "dev"
Requires-Dist: ruff>=0.4.4; extra == "dev"
Requires-Dist: pip-audit>=2.9.0; extra == "dev"
Requires-Dist: sphinx>=8.2.3; extra == "dev"
Requires-Dist: furo>=2024.8.6; extra == "dev"
Requires-Dist: sphinx-autobuild>=2024.10.3; extra == "dev"
Requires-Dist: sphinx-autodoc-typehints>=3.2.0; extra == "dev"
Requires-Dist: sphinx-copybutton>=0.5.2; extra == "dev"
Requires-Dist: docutils>=0.21.2; extra == "dev"
Requires-Dist: autodoc-pydantic>=2.2.0; extra == "dev"
Requires-Dist: pre-commit>=4.2.0; extra == "dev"
Dynamic: license-file
